biodata/__init__.py
biodata/auth.py
biodata/cli.py
biodata/config.py
biodata/enrich.py
biodata/gee_download.py
biodata/geometry.py
biodata/grid.py
biodata/history.py
biodata/output.py
biodata/provenance.py
biodata/qc.py
biodata/reducers.py
biodata/writers.py
biodata/adapters/__init__.py
biodata/adapters/base.py
biodata/adapters/local_raster.py
biodata_enricher-0.2.0.dist-info/licenses/LICENSE
biodata_enricher-0.2.0.dist-info/METADATA
biodata_enricher-0.2.0.dist-info/WHEEL
biodata_enricher-0.2.0.dist-info/entry_points.txt
biodata_enricher-0.2.0.dist-info/top_level.txt
biodata_enricher-0.2.0.dist-info/RECORD
