Metadata-Version: 2.4
Name: biodata-enricher
Version: 0.2.0
Summary: Enrich points with environmental predictors from local/remote sources (MVP).
Author-email: Team Biodata <team@example.com>
License: MIT
Project-URL: Homepage, https://github.com/AppleShay/biodata-enricher
Keywords: gis,raster,geospatial,environment,gee
Classifier: Programming Language :: Python :: 3
Classifier: Programming Language :: Python :: 3.10
Classifier: Programming Language :: Python :: 3.11
Classifier: Programming Language :: Python :: 3.12
Classifier: License :: OSI Approved :: MIT License
Classifier: Intended Audience :: Science/Research
Classifier: Topic :: Scientific/Engineering :: GIS
Requires-Python: >=3.10
License-File: LICENSE
Requires-Dist: pandas>=2.1
Requires-Dist: numpy>=1.26
Requires-Dist: pyproj>=3.6
Requires-Dist: rasterio>=1.3
Requires-Dist: shapely>=2.0
Requires-Dist: geopandas>=0.14
Requires-Dist: pyyaml>=6.0.1
Requires-Dist: pyarrow>=17.0.0
Provides-Extra: dev
Requires-Dist: pytest>=8.0; extra == "dev"
Requires-Dist: ruff>=0.5.0; extra == "dev"
Requires-Dist: black>=24.3.0; extra == "dev"
Provides-Extra: gee
Requires-Dist: earthengine-api>=0.1.398; extra == "gee"
Dynamic: license-file
